AbTune/__init__.py
AbTune/base.py
AbTune/esm_func.py
AbTune/fine_tune.py
AbTune/lora.py
AbTune/models.py
AbTune/run_AbTune.py
AbTune/utils.py
ab_tune-0.1.0.dist-info/METADATA
ab_tune-0.1.0.dist-info/WHEEL
ab_tune-0.1.0.dist-info/entry_points.txt
ab_tune-0.1.0.dist-info/top_level.txt
ab_tune-0.1.0.dist-info/RECORD
