Metadata-Version: 2.4
Name: Ab-Tune
Version: 0.1.0
Summary: AbTune: layer-wise selective Fine-Tuning of protein language models for Antibodies
Author-email: Xiaotong Xu <x.xu1@uu.nl>
License: MIT
Project-URL: homepage, https://github.com/ntxxt/Finetune-Ab.git
Requires-Python: >=3.10
Requires-Dist: biopython==1.85
Requires-Dist: fair-esm==2.0.0
Requires-Dist: numpy==1.26.4
Requires-Dist: omegaconf==2.3.0
Requires-Dist: pandas==2.2.3
Requires-Dist: torch==2.1.2
